{
	"pattrstorage" : 	{
		"name" : "winwinPresets",
		"slots" : 		{
			"1" : 			{
				"id" : 1,
				"data" : 				{
					"bp.MIDI to Signal::Bend" : [ 2.0 ],
					"bp.MIDI to Signal::ModWheelActivityLED" : [ 0.0 ],
					"bp.MIDI to Signal::NotePriority" : [ "Last Note Priority" ],
					"bp.MIDI to Signal::Triggering" : [ "Retrigger" ],
					"bp.MIDI to Signal::live.text" : [ 0.0 ],
					"bp.MIDI to Signal::note" : [ -0.666666666666666 ],
					"bp.MIDI to Signal::gate" : [ 0 ],
					"bp.MIDI to Signal::velocity" : [ 1.309523809523809 ],
					"bp.MIDI to Signal::mod" : [ 5.0 ],
					"bp.MIDI In::MIDIPort" : [ "nanoKEY2 KEYBOARD" ],
					"bp.MIDI In::PitchActivityLED" : [ 0.0 ],
					"bp.MIDI In::refresh" : [ 0.0 ],
					"bp.FM::Amt" : [ 0.0 ],
					"bp.FM::Depth" : [ 2.0 ],
					"bp.FM::Mute" : [ 0.0 ],
					"bp.FM::Offset" : [ -8.062992125984245 ],
					"bp.FM::Ratio" : [ 1.17 ],
					"bp.LPF::CV1" : [ 0.0 ],
					"bp.LPF::CV2" : [ 0.0 ],
					"bp.LPF::CV3" : [ 0.0 ],
					"bp.LPF::Freq" : [ 261.999999999999943 ],
					"bp.LPF::FreqMode" : [ 1.0 ],
					"bp.LPF::Offset" : [ 0.0 ],
					"bp.LPF::Res" : [ 0.0 ],
					"bp.LPF::ResCV" : [ 0.0 ],
					"bp.LPF::power[1]" : [ 0.0 ],
					"bp.ASR::Attack" : [ 100.0 ],
					"bp.ASR::Release" : [ 2525.196850393698696 ],
					"bp.ASR::Sustain" : [ 100.0 ],
					"bp.ASR::mute" : [ 0.0 ],
					"bp.Stereo::DSP" : [ 1.0 ],
					"bp.Stereo::Level" : [ -9.852202354776423 ],
					"bp.Stereo::Mute" : [ 0.0 ],
					"bp.Stereo::OutputChannel" : [ 0.0 ],
					"bp.VCA::Bypass" : [ 0.0 ],
					"bp.VCA::Quadrants" : [ 0.0 ],
					"bp.VCA::Response" : [ 0.0 ],
					"bp.Feedback Delay::Feedback" : [ -5.0 ],
					"bp.Feedback Delay::HPF" : [ 20.0 ],
					"bp.Feedback Delay::LPF" : [ 20000.0 ],
					"bp.Feedback Delay::Mix" : [ 83.858267716535423 ],
					"bp.Feedback Delay::bypass" : [ 0.0 ],
					"bp.Feedback Delay::time" : [ 200.0 ],
					"bp.Samplr::Loop" : [ 0.0 ],
					"bp.Samplr::LoopEnd" : [ 4814.603341190514584 ],
					"bp.Samplr::LoopStart" : [ 4438.004688704258115 ],
					"bp.Samplr::Loop[1]" : [ 1.0 ],
					"bp.Samplr::RecordGate" : [ 0.0 ],
					"bp.Samplr::Root" : [ 75.0 ],
					"bp.Samplr::SampleStart" : [ 0.0 ],
					"bp.Samplr::getsamplelength" : [ 0.0 ],
					"bp.Samplr::import" : [ 0.0 ],
					"bp.Samplr::power[1]" : [ 0.0 ],
					"bp.Samplr::write" : [ 0.0 ],
					"bp.Samplr::samplepth" : [ "Macintosh HD:/Users/markie/Library/Mobile Documents/com~apple~CloudDocs/PROJECTS/WIN WIN/Max stuff/Generative synths/What does a clarinet sound like (Ode to Joy).m4a" ],
					"bp.Recordr::AutoName" : [ 1.0 ],
					"bp.Recordr::Channels" : [ 1.0 ],
					"bp.Recordr::Format" : [ "int24" ],
					"bp.Recordr::Level" : [ 0.0 ],
					"bp.Recordr::Record" : [ 0.0 ],
					"bp.Recordr::getsamplelength" : [ 0.0 ],
					"bp.Signal Mixer::in3" : [ 0.913385826771653 ],
					"bp.Signal Mixer::in4" : [ 0.0 ],
					"bp.Signal Mixer::live.dial" : [ 0.401574803149606 ],
					"bp.Signal Mixer::live.dial[1]" : [ 1.0 ],
					"bp.Signal Mixer::power[1]" : [ 0.0 ],
					"bp.Stereo[1]::DSP" : [ 1.0 ],
					"bp.Stereo[1]::Level" : [ -6.343362657851735 ],
					"bp.Stereo[1]::Mute" : [ 0.0 ],
					"bp.Stereo[1]::OutputChannel" : [ 1.0 ],
					"bp.VCA[1]::Bypass" : [ 0.0 ],
					"bp.VCA[1]::Quadrants" : [ 0.0 ],
					"bp.VCA[1]::Response" : [ 0.0 ],
					"bp.FM[1]::Amt" : [ 0.0 ],
					"bp.FM[1]::Depth" : [ 7.635571746375064 ],
					"bp.FM[1]::Mute" : [ 0.0 ],
					"bp.FM[1]::Offset" : [ 4.031496062992119 ],
					"bp.FM[1]::Ratio" : [ 2.661064913131495 ]
				}

			}
,
			"2" : 			{
				"id" : 2,
				"data" : 				{
					"bp.MIDI to Signal::Bend" : [ 2.0 ],
					"bp.MIDI to Signal::ModWheelActivityLED" : [ 0.0 ],
					"bp.MIDI to Signal::NotePriority" : [ "Last Note Priority" ],
					"bp.MIDI to Signal::Triggering" : [ "Retrigger" ],
					"bp.MIDI to Signal::live.text" : [ 0.0 ],
					"bp.MIDI to Signal::note" : [ -0.25 ],
					"bp.MIDI to Signal::gate" : [ 0 ],
					"bp.MIDI to Signal::velocity" : [ 0.912698412698413 ],
					"bp.MIDI to Signal::mod" : [ 5.0 ],
					"bp.MIDI In::MIDIPort" : [ "nanoKEY2 KEYBOARD" ],
					"bp.MIDI In::PitchActivityLED" : [ 0.0 ],
					"bp.MIDI In::refresh" : [ 0.0 ],
					"bp.FM::Amt" : [ 0.0 ],
					"bp.FM::Depth" : [ 2.0 ],
					"bp.FM::Mute" : [ 0.0 ],
					"bp.FM::Offset" : [ 0.0 ],
					"bp.FM::Ratio" : [ 1.23 ],
					"bp.LPF::CV1" : [ 0.0 ],
					"bp.LPF::CV2" : [ 0.0 ],
					"bp.LPF::CV3" : [ 0.0 ],
					"bp.LPF::Freq" : [ 261.999999999999943 ],
					"bp.LPF::FreqMode" : [ 1.0 ],
					"bp.LPF::Offset" : [ 0.0 ],
					"bp.LPF::Res" : [ 0.0 ],
					"bp.LPF::ResCV" : [ 0.0 ],
					"bp.LPF::power[1]" : [ 0.0 ],
					"bp.ASR::Attack" : [ 100.0 ],
					"bp.ASR::Release" : [ 100.0 ],
					"bp.ASR::Sustain" : [ 100.0 ],
					"bp.ASR::mute" : [ 0.0 ],
					"bp.Stereo::DSP" : [ 1.0 ],
					"bp.Stereo::Level" : [ -9.852202354776423 ],
					"bp.Stereo::Mute" : [ 0.0 ],
					"bp.Stereo::OutputChannel" : [ 0.0 ],
					"bp.VCA::Bypass" : [ 0.0 ],
					"bp.VCA::Quadrants" : [ 0.0 ],
					"bp.VCA::Response" : [ 0.0 ],
					"bp.Feedback Delay::Feedback" : [ -72.0 ],
					"bp.Feedback Delay::HPF" : [ 20.0 ],
					"bp.Feedback Delay::LPF" : [ 20000.0 ],
					"bp.Feedback Delay::Mix" : [ 50.0 ],
					"bp.Feedback Delay::bypass" : [ 0.0 ],
					"bp.Feedback Delay::time" : [ 200.0 ],
					"bp.Samplr::Loop" : [ 1.0 ],
					"bp.Samplr::LoopEnd" : [ 1804.625912780966473 ],
					"bp.Samplr::LoopStart" : [ 1804.625912780966473 ],
					"bp.Samplr::Loop[1]" : [ 1.0 ],
					"bp.Samplr::RecordGate" : [ 0.0 ],
					"bp.Samplr::Root" : [ 60.0 ],
					"bp.Samplr::SampleStart" : [ 0.0 ],
					"bp.Samplr::getsamplelength" : [ 0.0 ],
					"bp.Samplr::import" : [ 0.0 ],
					"bp.Samplr::power[1]" : [ 0.0 ],
					"bp.Samplr::write" : [ 0.0 ],
					"bp.Samplr::samplepth" : [ "Macintosh HD:/Applications/Max.app/Contents/Resources/C74/media/msp/anton.aif" ],
					"bp.Recordr::AutoName" : [ 1.0 ],
					"bp.Recordr::Channels" : [ 1.0 ],
					"bp.Recordr::Format" : [ "int24" ],
					"bp.Recordr::Level" : [ -13.464567000000001 ],
					"bp.Recordr::Record" : [ 0.0 ],
					"bp.Recordr::getsamplelength" : [ 0.0 ],
					"bp.Signal Mixer::in3" : [ 0.0 ],
					"bp.Signal Mixer::in4" : [ 0.0 ],
					"bp.Signal Mixer::live.dial" : [ 0.559055118110236 ],
					"bp.Signal Mixer::live.dial[1]" : [ 0.267716535433071 ],
					"bp.Signal Mixer::power[1]" : [ 0.0 ],
					"bp.Stereo[1]::DSP" : [  ],
					"bp.Stereo[1]::Level" : [  ],
					"bp.Stereo[1]::Mute" : [  ],
					"bp.Stereo[1]::OutputChannel" : [  ],
					"bp.VCA[1]::Bypass" : [  ],
					"bp.VCA[1]::Quadrants" : [  ],
					"bp.VCA[1]::Response" : [  ],
					"bp.FM[1]::Amt" : [  ],
					"bp.FM[1]::Depth" : [  ],
					"bp.FM[1]::Mute" : [  ],
					"bp.FM[1]::Offset" : [  ],
					"bp.FM[1]::Ratio" : [  ]
				}

			}
,
			"3" : 			{
				"id" : 3,
				"data" : 				{
					"bp.MIDI to Signal::Bend" : [ 2.0 ],
					"bp.MIDI to Signal::ModWheelActivityLED" : [ 0.0 ],
					"bp.MIDI to Signal::NotePriority" : [ "Last Note Priority" ],
					"bp.MIDI to Signal::Triggering" : [ "Retrigger" ],
					"bp.MIDI to Signal::live.text" : [ 0.0 ],
					"bp.MIDI to Signal::note" : [ -0.25 ],
					"bp.MIDI to Signal::gate" : [ 0 ],
					"bp.MIDI to Signal::velocity" : [ 2.380952380952381 ],
					"bp.MIDI to Signal::mod" : [ 5.0 ],
					"bp.MIDI In::MIDIPort" : [ "nanoKEY2 KEYBOARD" ],
					"bp.MIDI In::PitchActivityLED" : [ 0.0 ],
					"bp.MIDI In::refresh" : [ 0.0 ],
					"bp.FM::Amt" : [ 0.0 ],
					"bp.FM::Depth" : [ 2.0 ],
					"bp.FM::Mute" : [ 0.0 ],
					"bp.FM::Offset" : [ -8.062992125984245 ],
					"bp.FM::Ratio" : [ 1.22 ],
					"bp.LPF::CV1" : [ 0.0 ],
					"bp.LPF::CV2" : [ 0.0 ],
					"bp.LPF::CV3" : [ 0.0 ],
					"bp.LPF::Freq" : [ 261.999999999999943 ],
					"bp.LPF::FreqMode" : [ 1.0 ],
					"bp.LPF::Offset" : [ 0.0 ],
					"bp.LPF::Res" : [ 0.0 ],
					"bp.LPF::ResCV" : [ 0.0 ],
					"bp.LPF::power[1]" : [ 0.0 ],
					"bp.ASR::Attack" : [ 100.0 ],
					"bp.ASR::Release" : [ 2525.196850393698696 ],
					"bp.ASR::Sustain" : [ 100.0 ],
					"bp.ASR::mute" : [ 0.0 ],
					"bp.Stereo::DSP" : [ 1.0 ],
					"bp.Stereo::Level" : [ -9.852202354776423 ],
					"bp.Stereo::Mute" : [ 0.0 ],
					"bp.Stereo::OutputChannel" : [ 0.0 ],
					"bp.VCA::Bypass" : [ 0.0 ],
					"bp.VCA::Quadrants" : [ 0.0 ],
					"bp.VCA::Response" : [ 0.0 ],
					"bp.Feedback Delay::Feedback" : [ -11.600000000000001 ],
					"bp.Feedback Delay::HPF" : [ 20.0 ],
					"bp.Feedback Delay::LPF" : [ 20000.0 ],
					"bp.Feedback Delay::Mix" : [ 50.0 ],
					"bp.Feedback Delay::bypass" : [ 0.0 ],
					"bp.Feedback Delay::time" : [ 200.0 ],
					"bp.Samplr::Loop" : [ 1.0 ],
					"bp.Samplr::LoopEnd" : [ 4814.603341190514584 ],
					"bp.Samplr::LoopStart" : [ 4438.004688704258115 ],
					"bp.Samplr::Loop[1]" : [ 1.0 ],
					"bp.Samplr::RecordGate" : [ 0.0 ],
					"bp.Samplr::Root" : [ 75.0 ],
					"bp.Samplr::SampleStart" : [ 0.0 ],
					"bp.Samplr::getsamplelength" : [ 0.0 ],
					"bp.Samplr::import" : [ 0.0 ],
					"bp.Samplr::power[1]" : [ 0.0 ],
					"bp.Samplr::write" : [ 0.0 ],
					"bp.Samplr::samplepth" : [ "Macintosh HD:/Users/markie/Library/Mobile Documents/com~apple~CloudDocs/PROJECTS/WIN WIN/Max stuff/Generative synths/What does a clarinet sound like (Ode to Joy).m4a" ],
					"bp.Recordr::AutoName" : [ 1.0 ],
					"bp.Recordr::Channels" : [ 1.0 ],
					"bp.Recordr::Format" : [ "int24" ],
					"bp.Recordr::Level" : [ 0.0 ],
					"bp.Recordr::Record" : [ 0.0 ],
					"bp.Recordr::getsamplelength" : [ 0.0 ],
					"bp.Signal Mixer::in3" : [ 0.0 ],
					"bp.Signal Mixer::in4" : [ 0.0 ],
					"bp.Signal Mixer::live.dial" : [ 0.401574803149606 ],
					"bp.Signal Mixer::live.dial[1]" : [ 1.0 ],
					"bp.Signal Mixer::power[1]" : [ 0.0 ],
					"bp.Stereo[1]::DSP" : [ 1.0 ],
					"bp.Stereo[1]::Level" : [ -6.343362657851735 ],
					"bp.Stereo[1]::Mute" : [ 0.0 ],
					"bp.Stereo[1]::OutputChannel" : [ 1.0 ],
					"bp.VCA[1]::Bypass" : [  ],
					"bp.VCA[1]::Quadrants" : [  ],
					"bp.VCA[1]::Response" : [  ],
					"bp.FM[1]::Amt" : [  ],
					"bp.FM[1]::Depth" : [  ],
					"bp.FM[1]::Mute" : [  ],
					"bp.FM[1]::Offset" : [  ],
					"bp.FM[1]::Ratio" : [  ]
				}

			}
,
			"4" : 			{
				"id" : 4,
				"data" : 				{
					"bp.MIDI to Signal::Bend" : [ 2.0 ],
					"bp.MIDI to Signal::ModWheelActivityLED" : [ 0.0 ],
					"bp.MIDI to Signal::NotePriority" : [ "Last Note Priority" ],
					"bp.MIDI to Signal::Triggering" : [ "Retrigger" ],
					"bp.MIDI to Signal::live.text" : [ 0.0 ],
					"bp.MIDI to Signal::note" : [ -0.833333333333333 ],
					"bp.MIDI to Signal::gate" : [ 0 ],
					"bp.MIDI to Signal::velocity" : [ 1.825396825396825 ],
					"bp.MIDI to Signal::mod" : [ 5.0 ],
					"bp.MIDI In::MIDIPort" : [ "nanoKEY2 KEYBOARD" ],
					"bp.MIDI In::PitchActivityLED" : [ 0.0 ],
					"bp.MIDI In::refresh" : [ 0.0 ],
					"bp.FM::Amt" : [ 0.0 ],
					"bp.FM::Depth" : [ 2.0 ],
					"bp.FM::Mute" : [ 0.0 ],
					"bp.FM::Offset" : [ -8.062992125984245 ],
					"bp.FM::Ratio" : [ 1.17 ],
					"bp.LPF::CV1" : [ 0.0 ],
					"bp.LPF::CV2" : [ 0.0 ],
					"bp.LPF::CV3" : [ 0.0 ],
					"bp.LPF::Freq" : [ 261.999999999999943 ],
					"bp.LPF::FreqMode" : [ 1.0 ],
					"bp.LPF::Offset" : [ 0.0 ],
					"bp.LPF::Res" : [ 0.0 ],
					"bp.LPF::ResCV" : [ 0.0 ],
					"bp.LPF::power[1]" : [ 0.0 ],
					"bp.ASR::Attack" : [ 100.0 ],
					"bp.ASR::Release" : [ 2525.196850393698696 ],
					"bp.ASR::Sustain" : [ 100.0 ],
					"bp.ASR::mute" : [ 0.0 ],
					"bp.Stereo::DSP" : [ 0.0 ],
					"bp.Stereo::Level" : [ -9.852202354776423 ],
					"bp.Stereo::Mute" : [ 0.0 ],
					"bp.Stereo::OutputChannel" : [ 0.0 ],
					"bp.VCA::Bypass" : [ 0.0 ],
					"bp.VCA::Quadrants" : [ 0.0 ],
					"bp.VCA::Response" : [ 0.0 ],
					"bp.Feedback Delay::Feedback" : [ -5.0 ],
					"bp.Feedback Delay::HPF" : [ 20.0 ],
					"bp.Feedback Delay::LPF" : [ 20000.0 ],
					"bp.Feedback Delay::Mix" : [ 83.858267716535423 ],
					"bp.Feedback Delay::bypass" : [ 0.0 ],
					"bp.Feedback Delay::time" : [ 200.0 ],
					"bp.Samplr::Loop" : [ 0.0 ],
					"bp.Samplr::LoopEnd" : [ 4814.603341190514584 ],
					"bp.Samplr::LoopStart" : [ 4438.004688704258115 ],
					"bp.Samplr::Loop[1]" : [ 1.0 ],
					"bp.Samplr::RecordGate" : [ 0.0 ],
					"bp.Samplr::Root" : [ 75.0 ],
					"bp.Samplr::SampleStart" : [ 0.0 ],
					"bp.Samplr::getsamplelength" : [ 0.0 ],
					"bp.Samplr::import" : [ 0.0 ],
					"bp.Samplr::power[1]" : [ 0.0 ],
					"bp.Samplr::write" : [ 0.0 ],
					"bp.Samplr::samplepth" : [ "Macintosh HD:/Users/markie/Library/Mobile Documents/com~apple~CloudDocs/PROJECTS/WIN WIN/Max stuff/Generative synths/What does a clarinet sound like (Ode to Joy).m4a" ],
					"bp.Recordr::AutoName" : [ 1.0 ],
					"bp.Recordr::Channels" : [ 1.0 ],
					"bp.Recordr::Format" : [ "int24" ],
					"bp.Recordr::Level" : [ 0.0 ],
					"bp.Recordr::Record" : [ 0.0 ],
					"bp.Recordr::getsamplelength" : [ 0.0 ],
					"bp.Signal Mixer::in3" : [ 0.0 ],
					"bp.Signal Mixer::in4" : [ 0.0 ],
					"bp.Signal Mixer::live.dial" : [ 0.401574803149606 ],
					"bp.Signal Mixer::live.dial[1]" : [ 1.0 ],
					"bp.Signal Mixer::power[1]" : [ 0.0 ],
					"bp.Stereo[1]::DSP" : [ 0.0 ],
					"bp.Stereo[1]::Level" : [ -6.343362657851735 ],
					"bp.Stereo[1]::Mute" : [ 0.0 ],
					"bp.Stereo[1]::OutputChannel" : [ 1.0 ],
					"bp.VCA[1]::Bypass" : [  ],
					"bp.VCA[1]::Quadrants" : [  ],
					"bp.VCA[1]::Response" : [  ],
					"bp.FM[1]::Amt" : [  ],
					"bp.FM[1]::Depth" : [  ],
					"bp.FM[1]::Mute" : [  ],
					"bp.FM[1]::Offset" : [  ],
					"bp.FM[1]::Ratio" : [  ]
				}

			}
,
			"5" : 			{
				"id" : 5,
				"data" : 				{
					"bp.MIDI to Signal::Bend" : [ 2.0 ],
					"bp.MIDI to Signal::ModWheelActivityLED" : [ 0.0 ],
					"bp.MIDI to Signal::NotePriority" : [ "Last Note Priority" ],
					"bp.MIDI to Signal::Triggering" : [ "Retrigger" ],
					"bp.MIDI to Signal::live.text" : [ 0.0 ],
					"bp.MIDI to Signal::note" : [ -0.666666666666666 ],
					"bp.MIDI to Signal::gate" : [ 0 ],
					"bp.MIDI to Signal::velocity" : [ 1.111111111111111 ],
					"bp.MIDI to Signal::mod" : [ 5.0 ],
					"bp.MIDI In::MIDIPort" : [ "nanoKEY2 KEYBOARD" ],
					"bp.MIDI In::PitchActivityLED" : [ 0.0 ],
					"bp.MIDI In::refresh" : [ 0.0 ],
					"bp.FM::Amt" : [ 0.0 ],
					"bp.FM::Depth" : [ 2.0 ],
					"bp.FM::Mute" : [ 0.0 ],
					"bp.FM::Offset" : [ -9.070866141732267 ],
					"bp.FM::Ratio" : [ 1.571428571428572 ],
					"bp.LPF::CV1" : [ 0.0 ],
					"bp.LPF::CV2" : [ 0.0 ],
					"bp.LPF::CV3" : [ 0.0 ],
					"bp.LPF::Freq" : [ 261.999999999999943 ],
					"bp.LPF::FreqMode" : [ 1.0 ],
					"bp.LPF::Offset" : [ 0.0 ],
					"bp.LPF::Res" : [ 0.0 ],
					"bp.LPF::ResCV" : [ 0.0 ],
					"bp.LPF::power[1]" : [ 0.0 ],
					"bp.ASR::Attack" : [ 100.0 ],
					"bp.ASR::Release" : [ 2525.196850393698696 ],
					"bp.ASR::Sustain" : [ 100.0 ],
					"bp.ASR::mute" : [ 0.0 ],
					"bp.Stereo::DSP" : [ 1.0 ],
					"bp.Stereo::Level" : [ -9.852202354776423 ],
					"bp.Stereo::Mute" : [ 0.0 ],
					"bp.Stereo::OutputChannel" : [ 0.0 ],
					"bp.VCA::Bypass" : [ 0.0 ],
					"bp.VCA::Quadrants" : [ 0.0 ],
					"bp.VCA::Response" : [ 0.0 ],
					"bp.Feedback Delay::Feedback" : [ -5.0 ],
					"bp.Feedback Delay::HPF" : [ 20.0 ],
					"bp.Feedback Delay::LPF" : [ 20000.0 ],
					"bp.Feedback Delay::Mix" : [ 83.858267716535423 ],
					"bp.Feedback Delay::bypass" : [ 0.0 ],
					"bp.Feedback Delay::time" : [ 200.0 ],
					"bp.Samplr::Loop" : [ 1.0 ],
					"bp.Samplr::LoopEnd" : [ 4814.603341190514584 ],
					"bp.Samplr::LoopStart" : [ 4438.004688704258115 ],
					"bp.Samplr::Loop[1]" : [ 1.0 ],
					"bp.Samplr::RecordGate" : [ 0.0 ],
					"bp.Samplr::Root" : [ 75.0 ],
					"bp.Samplr::SampleStart" : [ 0.0 ],
					"bp.Samplr::getsamplelength" : [ 0.0 ],
					"bp.Samplr::import" : [ 0.0 ],
					"bp.Samplr::power[1]" : [ 0.0 ],
					"bp.Samplr::write" : [ 0.0 ],
					"bp.Samplr::samplepth" : [ "Macintosh HD:/Users/markie/Library/Mobile Documents/com~apple~CloudDocs/PROJECTS/WIN WIN/Max stuff/Generative synths/What does a clarinet sound like (Ode to Joy).m4a" ],
					"bp.Recordr::AutoName" : [ 1.0 ],
					"bp.Recordr::Channels" : [ 1.0 ],
					"bp.Recordr::Format" : [ "int24" ],
					"bp.Recordr::Level" : [ 0.0 ],
					"bp.Recordr::Record" : [ 0.0 ],
					"bp.Recordr::getsamplelength" : [ 0.0 ],
					"bp.Signal Mixer::in3" : [ 0.913385826771653 ],
					"bp.Signal Mixer::in4" : [ 0.0 ],
					"bp.Signal Mixer::live.dial" : [ 0.401574803149606 ],
					"bp.Signal Mixer::live.dial[1]" : [ 1.0 ],
					"bp.Signal Mixer::power[1]" : [ 0.0 ],
					"bp.Stereo[1]::DSP" : [ 1.0 ],
					"bp.Stereo[1]::Level" : [ -6.343362657851735 ],
					"bp.Stereo[1]::Mute" : [ 0.0 ],
					"bp.Stereo[1]::OutputChannel" : [ 1.0 ],
					"bp.VCA[1]::Bypass" : [ 0.0 ],
					"bp.VCA[1]::Quadrants" : [ 0.0 ],
					"bp.VCA[1]::Response" : [ 0.0 ],
					"bp.FM[1]::Amt" : [ 0.0 ],
					"bp.FM[1]::Depth" : [ 7.635571746375064 ],
					"bp.FM[1]::Mute" : [ 0.0 ],
					"bp.FM[1]::Offset" : [ 4.031496062992119 ],
					"bp.FM[1]::Ratio" : [ 2.661064913131495 ]
				}

			}
,
			"6" : 			{
				"id" : 6,
				"data" : 				{
					"bp.MIDI to Signal::Bend" : [ 2.0 ],
					"bp.MIDI to Signal::ModWheelActivityLED" : [ 0.0 ],
					"bp.MIDI to Signal::NotePriority" : [ "Last Note Priority" ],
					"bp.MIDI to Signal::Triggering" : [ "Retrigger" ],
					"bp.MIDI to Signal::live.text" : [ 0.0 ],
					"bp.MIDI to Signal::note" : [ -0.833333333333333 ],
					"bp.MIDI to Signal::gate" : [ 5 ],
					"bp.MIDI to Signal::velocity" : [ 2.5 ],
					"bp.MIDI to Signal::mod" : [ 5.0 ],
					"bp.MIDI In::MIDIPort" : [ "nanoKEY2 KEYBOARD" ],
					"bp.MIDI In::PitchActivityLED" : [ 0.0 ],
					"bp.MIDI In::refresh" : [ 0.0 ],
					"bp.FM::Amt" : [ 0.0 ],
					"bp.FM::Depth" : [ 2.0 ],
					"bp.FM::Mute" : [ 0.0 ],
					"bp.FM::Offset" : [ -9.070866141732267 ],
					"bp.FM::Ratio" : [ 1.772727272727273 ],
					"bp.LPF::CV1" : [ 0.0 ],
					"bp.LPF::CV2" : [ 0.0 ],
					"bp.LPF::CV3" : [ 0.0 ],
					"bp.LPF::Freq" : [ 343.201619056194431 ],
					"bp.LPF::FreqMode" : [ 0.0 ],
					"bp.LPF::Offset" : [ 0.0 ],
					"bp.LPF::Res" : [ 0.0 ],
					"bp.LPF::ResCV" : [ 0.0 ],
					"bp.LPF::power[1]" : [ 0.0 ],
					"bp.ASR::Attack" : [ 100.0 ],
					"bp.ASR::Release" : [ 2525.196850393698696 ],
					"bp.ASR::Sustain" : [ 100.0 ],
					"bp.ASR::mute" : [ 0.0 ],
					"bp.Stereo::DSP" : [ 1.0 ],
					"bp.Stereo::Level" : [ -9.852202354776423 ],
					"bp.Stereo::Mute" : [ 0.0 ],
					"bp.Stereo::OutputChannel" : [ 0.0 ],
					"bp.VCA::Bypass" : [ 0.0 ],
					"bp.VCA::Quadrants" : [ 0.0 ],
					"bp.VCA::Response" : [ 0.0 ],
					"bp.Feedback Delay::Feedback" : [ -0.863057649845985 ],
					"bp.Feedback Delay::HPF" : [ 20.0 ],
					"bp.Feedback Delay::LPF" : [ 20000.0 ],
					"bp.Feedback Delay::Mix" : [ 83.858267716535423 ],
					"bp.Feedback Delay::bypass" : [ 0.0 ],
					"bp.Feedback Delay::time" : [ 593.70078740157453 ],
					"bp.Samplr::Loop" : [ 1.0 ],
					"bp.Samplr::LoopEnd" : [ 6701.134018710181408 ],
					"bp.Samplr::LoopStart" : [ 5381.542136317044424 ],
					"bp.Samplr::Loop[1]" : [ 1.0 ],
					"bp.Samplr::RecordGate" : [ 0.0 ],
					"bp.Samplr::Root" : [ 75.0 ],
					"bp.Samplr::SampleStart" : [ 0.0 ],
					"bp.Samplr::getsamplelength" : [ 0.0 ],
					"bp.Samplr::import" : [ 0.0 ],
					"bp.Samplr::power[1]" : [ 0.0 ],
					"bp.Samplr::write" : [ 0.0 ],
					"bp.Samplr::samplepth" : [ "Macintosh HD:/Users/markie/Library/Mobile Documents/com~apple~CloudDocs/PROJECTS/WIN WIN/Max stuff/Generative synths/ClarinetOde.m4a" ],
					"bp.Recordr::AutoName" : [ 1.0 ],
					"bp.Recordr::Channels" : [ 1.0 ],
					"bp.Recordr::Format" : [ "int24" ],
					"bp.Recordr::Level" : [ 0.0 ],
					"bp.Recordr::Record" : [ 0.0 ],
					"bp.Recordr::getsamplelength" : [ 0.0 ],
					"bp.Signal Mixer::in3" : [ 0.732283464566928 ],
					"bp.Signal Mixer::in4" : [ 0.0 ],
					"bp.Signal Mixer::live.dial" : [ 0.338582677165354 ],
					"bp.Signal Mixer::live.dial[1]" : [ 1.0 ],
					"bp.Signal Mixer::power[1]" : [ 0.0 ],
					"bp.Stereo[1]::DSP" : [ 1.0 ],
					"bp.Stereo[1]::Level" : [ -6.343362657851735 ],
					"bp.Stereo[1]::Mute" : [ 0.0 ],
					"bp.Stereo[1]::OutputChannel" : [ 1.0 ],
					"bp.VCA[1]::Bypass" : [ 0.0 ],
					"bp.VCA[1]::Quadrants" : [ 0.0 ],
					"bp.VCA[1]::Response" : [ 0.0 ],
					"bp.FM[1]::Amt" : [ 0.0 ],
					"bp.FM[1]::Depth" : [ 7.635571746375064 ],
					"bp.FM[1]::Mute" : [ 0.0 ],
					"bp.FM[1]::Offset" : [ 4.031496062992119 ],
					"bp.FM[1]::Ratio" : [ 2.661064913131495 ]
				}

			}

		}

	}

}
